pyplanemono_minimal/__init__.py
pyplanemono_minimal/elements/__init__.py
pyplanemono_minimal/elements/grating.py
pyplanemono_minimal/elements/mirror.py
pyplanemono_minimal/elements/pgm.py
pyplanemono_minimal/geometry/__init__.py
pyplanemono_minimal/geometry/geometry.py
pyplanemono_minimal-1.0.dist-info/LICENSE
pyplanemono_minimal-1.0.dist-info/METADATA
pyplanemono_minimal-1.0.dist-info/WHEEL
pyplanemono_minimal-1.0.dist-info/top_level.txt
pyplanemono_minimal-1.0.dist-info/RECORD
