Metadata-Version: 2.1
Name: pyplanemono_minimal
Version: 1.0
Summary: X-ray tracing for plane grating monochromator. Minimal version with no interface to SHADOW.
Author-email: Patrick Wang <patrick.wang@diamond.ac.uk>
Classifier: Programming Language :: Python :: 3
Classifier: License :: OSI Approved :: MIT License
Classifier: Operating System :: OS Independent
Requires-Python: >=3.8.0
License-File: LICENSE
Requires-Dist: numpy >=1.23.0
Requires-Dist: scipy >=1.8.1
Requires-Dist: matplotlib >=3.5.2
